{
    "name": "FORCE-BLACKRAIN",
    "icon": "SquadSymbols_13",
    "description": "GUILDE+FRANCAISE+AMBIANCE+SAINE+ET+MATURE+FORCE+ET+HONNEUR",
    "membershipRestrictions": {
        "openEnrollment": true,
        "maxSize": 30,
        "minScoreAtEnrollment": 0,
        "faction": "rebel"
    },
    "members": [
        {
            "name": "Deldevaudes",
            "isOwner": true,
            "isOfficer": true,
            "joinDate": 1463243931,
            "troopsDonated": 2503,
            "troopsReceived": 2519,
            "rank": 1,
            "hqLevel": 8,
            "reputationInvested": 272,
            "xp": 1972,
            "score": 8638,
            "warParty": 1,
            "tournamentRating": 0,
            "tournamentScores": {
                "planet23": 0,
                "planet8": 0
            },
            "attacksWon": 1514,
            "defensesWon": 179,
            "planet": "planet1",
            "lastLoginTime": 1490453949,
            "lastUpdated": 1490495917,
            "hasPlanetaryCommand": true,
            "playerId": "852b6981-92ec-11e5-bb79-06a77e004fbb"
        },
        {
            "name": "Talon Karrde",
            "isOwner": false,
            "isOfficer": false,
            "joinDate": 1477367231,
            "troopsDonated": 1741,
            "troopsReceived": 1449,
            "rank": 2,
            "hqLevel": 7,
            "reputationInvested": 205,
            "xp": 1649,
            "score": 5619,
            "warParty": 1,
            "tournamentRating": 0,
            "tournamentScores": {
                "planet23": 0,
                "planet8": 0
            },
            "attacksWon": 765,
            "defensesWon": 64,
            "planet": "planet1",
            "lastLoginTime": 1490469922,
            "lastUpdated": 1490494811,
            "hasPlanetaryCommand": true,
            "playerId": "ba4d3e48-8352-11e6-94fe-06cb44004f79"
        },
        {
            "name": "skimaster",
            "isOwner": false,
            "isOfficer": false,
            "joinDate": 1483731882,
            "troopsDonated": 111,
            "troopsReceived": 627,
            "rank": 3,
            "hqLevel": 6,
            "reputationInvested": 40,
            "xp": 1179,
            "score": 2056,
            "warParty": 1,
            "tournamentRating": 0,
            "tournamentScores": {
                "planet23": 0,
                "planet8": 0
            },
            "attacksWon": 377,
            "defensesWon": 27,
            "planet": "planet1",
            "lastLoginTime": 1490481108,
            "lastUpdated": 1490481114,
            "hasPlanetaryCommand": true,
            "playerId": "f647afde-d43f-11e6-8f8c-06c66a004f76"
        },
        {
            "name": "chawolf",
            "isOwner": false,
            "isOfficer": false,
            "joinDate": 1482947810,
            "troopsDonated": 441,
            "troopsReceived": 294,
            "rank": 4,
            "hqLevel": 6,
            "reputationInvested": 40,
            "xp": 1265,
            "score": 1593,
            "warParty": 1,
            "tournamentRating": 0,
            "tournamentScores": {
                "planet23": 0,
                "planet8": 0
            },
            "attacksWon": 535,
            "defensesWon": 107,
            "planet": "planet1",
            "lastLoginTime": 1489888256,
            "lastUpdated": 1490488138,
            "hasPlanetaryCommand": true,
            "playerId": "f7f0cb5f-acd2-11e4-a82d-06dc8c004fbd"
        },
        {
            "name": "QuintusDel",
            "isOwner": false,
            "isOfficer": true,
            "joinDate": 1480440764,
            "troopsDonated": 279,
            "troopsReceived": 283,
            "rank": 5,
            "hqLevel": 6,
            "reputationInvested": 81,
            "xp": 1155,
            "score": 1269,
            "warParty": 1,
            "tournamentRating": 0,
            "tournamentScores": {
                "planet23": 0,
                "planet8": 0
            },
            "attacksWon": 228,
            "defensesWon": 70,
            "planet": "planet1",
            "lastLoginTime": 1490439974,
            "lastUpdated": 1490467889,
            "hasPlanetaryCommand": false,
            "playerId": "a4b08e4c-3f4b-11e6-91e4-061c98004f78"
        },
        {
            "name": "Trident",
            "isOwner": false,
            "isOfficer": false,
            "joinDate": 1487424967,
            "troopsDonated": 174,
            "troopsReceived": 120,
            "rank": 6,
            "hqLevel": 6,
            "reputationInvested": 0,
            "xp": 997,
            "score": 422,
            "warParty": 1,
            "tournamentRating": 0,
            "tournamentScores": {
                "planet23": 0,
                "planet8": 0
            },
            "attacksWon": 42,
            "defensesWon": 6,
            "planet": "planet1",
            "lastLoginTime": 1490487897,
            "lastUpdated": 1490487899,
            "hasPlanetaryCommand": false,
            "playerId": "3acbde27-f4d1-11e6-804c-069da4004f8b"
        },
        {
            "name": "Crusher",
            "isOwner": false,
            "isOfficer": false,
            "joinDate": 1478728280,
            "troopsDonated": 231,
            "troopsReceived": 143,
            "rank": 7,
            "hqLevel": 5,
            "reputationInvested": 29,
            "xp": 872,
            "score": 284,
            "warParty": 0,
            "tournamentRating": 0,
            "tournamentScores": {
                "planet23": 0,
                "planet8": 0
            },
            "attacksWon": 313,
            "defensesWon": 9,
            "planet": "planet6",
            "lastLoginTime": 1488411028,
            "lastUpdated": 1490453464,
            "hasPlanetaryCommand": true,
            "playerId": "c3158d26-6505-11e6-b388-06e6ee004fbc"
        },
        {
            "name": "Gula",
            "isOwner": false,
            "isOfficer": false,
            "joinDate": 1489030127,
            "troopsDonated": 28,
            "troopsReceived": 0,
            "rank": 8,
            "hqLevel": 4,
            "reputationInvested": 0,
            "xp": 580,
            "score": 216,
            "warParty": 1,
            "tournamentRating": 0,
            "tournamentScores": {
                "planet23": 0,
                "planet8": 0
            },
            "attacksWon": 52,
            "defensesWon": 4,
            "planet": "planet1",
            "lastLoginTime": 1489333265,
            "lastUpdated": 1490474247,
            "hasPlanetaryCommand": false,
            "playerId": "893401fc-fec8-11e6-b985-06a77e004fbb"
        },
        {
            "name": "gabesz33",
            "isOwner": false,
            "isOfficer": false,
            "joinDate": 1489544960,
            "troopsDonated": 0,
            "troopsReceived": 23,
            "rank": 9,
            "hqLevel": 5,
            "reputationInvested": 0,
            "xp": 621,
            "score": 195,
            "warParty": 1,
            "tournamentRating": 0,
            "tournamentScores": {
                "planet23": 0,
                "planet8": 0
            },
            "attacksWon": 35,
            "defensesWon": 0,
            "planet": "planet1",
            "lastLoginTime": 1490497431,
            "lastUpdated": 1490497629,
            "hasPlanetaryCommand": false,
            "playerId": "cfbc34c8-0924-11e7-ba0b-060a32004f8c"
        },
        {
            "name": "gouloume",
            "isOwner": false,
            "isOfficer": false,
            "joinDate": 1485357844,
            "troopsDonated": 0,
            "troopsReceived": 0,
            "rank": 10,
            "hqLevel": 4,
            "reputationInvested": 0,
            "xp": 459,
            "score": 161,
            "warParty": 0,
            "tournamentRating": 0,
            "tournamentScores": {
                "planet23": 0,
                "planet8": 0
            },
            "attacksWon": 19,
            "defensesWon": 4,
            "planet": "planet1",
            "lastLoginTime": 1488111531,
            "lastUpdated": 1490400202,
            "hasPlanetaryCommand": false,
            "playerId": "32f11f0e-db23-11e6-95c1-063864004f75"
        },
        {
            "name": "52067",
            "isOwner": false,
            "isOfficer": false,
            "joinDate": 1489663303,
            "troopsDonated": 0,
            "troopsReceived": 37,
            "rank": 11,
            "hqLevel": 4,
            "reputationInvested": 0,
            "xp": 550,
            "score": 152,
            "warParty": 1,
            "tournamentRating": 0,
            "tournamentScores": {
                "planet23": 0,
                "planet8": 0
            },
            "attacksWon": 16,
            "defensesWon": 0,
            "planet": "planet1",
            "lastLoginTime": 1490440422,
            "lastUpdated": 1490440428,
            "hasPlanetaryCommand": false,
            "playerId": "726945ce-015c-11e7-953a-06033c004f77"
        },
        {
            "name": "MISTERSNIPER",
            "isOwner": false,
            "isOfficer": false,
            "joinDate": 1488910303,
            "troopsDonated": 0,
            "troopsReceived": 0,
            "rank": 12,
            "hqLevel": 3,
            "reputationInvested": 0,
            "xp": 307,
            "score": 115,
            "warParty": 1,
            "tournamentRating": 0,
            "tournamentScores": {
                "planet23": 0,
                "planet8": 0
            },
            "attacksWon": 3,
            "defensesWon": 1,
            "planet": "planet1",
            "lastLoginTime": 1489499517,
            "lastUpdated": 1490312004,
            "hasPlanetaryCommand": false,
            "playerId": "6a5e63bb-f4fe-11e6-91d6-06e6ee004fbc"
        },
        {
            "name": "ячвіві",
            "isOwner": false,
            "isOfficer": false,
            "joinDate": 1489865388,
            "troopsDonated": 0,
            "troopsReceived": 0,
            "rank": 13,
            "hqLevel": 2,
            "reputationInvested": 0,
            "xp": 182,
            "score": 110,
            "warParty": 0,
            "tournamentRating": 0,
            "tournamentScores": null,
            "attacksWon": 2,
            "defensesWon": 0,
            "planet": "planet1",
            "lastLoginTime": 1489864781,
            "lastUpdated": 1489865389,
            "hasPlanetaryCommand": false,
            "playerId": "447e6da2-0c07-11e7-999d-069da4004f8b"
        },
        {
            "name": "rok",
            "isOwner": false,
            "isOfficer": false,
            "joinDate": 1489544587,
            "troopsDonated": 0,
            "troopsReceived": 2,
            "rank": 14,
            "hqLevel": 2,
            "reputationInvested": 0,
            "xp": 207,
            "score": 108,
            "warParty": 0,
            "tournamentRating": 0,
            "tournamentScores": {
                "planet6": 0
            },
            "attacksWon": 5,
            "defensesWon": 0,
            "planet": "planet1",
            "lastLoginTime": 1489893560,
            "lastUpdated": 1489893570,
            "hasPlanetaryCommand": false,
            "playerId": "972cf49d-0785-11e7-9236-063864004f75"
        },
        {
            "name": "Rex",
            "isOwner": false,
            "isOfficer": false,
            "joinDate": 1489212101,
            "troopsDonated": 0,
            "troopsReceived": 8,
            "rank": 15,
            "hqLevel": 2,
            "reputationInvested": 0,
            "xp": 150,
            "score": 105,
            "warParty": 0,
            "tournamentRating": 0,
            "tournamentScores": {
                "planet6": 0
            },
            "attacksWon": 1,
            "defensesWon": 0,
            "planet": "planet1",
            "lastLoginTime": 1489926634,
            "lastUpdated": 1489926960,
            "hasPlanetaryCommand": false,
            "playerId": "321e663f-04ee-11e7-b7db-06a77e004fbb"
        },
        {
            "name": "thielu190712",
            "isOwner": false,
            "isOfficer": false,
            "joinDate": 1488750201,
            "troopsDonated": 0,
            "troopsReceived": 0,
            "rank": 16,
            "hqLevel": 2,
            "reputationInvested": 0,
            "xp": 126,
            "score": 100,
            "warParty": 0,
            "tournamentRating": 0,
            "tournamentScores": null,
            "attacksWon": 0,
            "defensesWon": 0,
            "planet": "planet1",
            "lastLoginTime": 1488749886,
            "lastUpdated": 1488750202,
            "hasPlanetaryCommand": false,
            "playerId": "bd8220fa-f1f9-11e4-96f7-06dc8c004fbd"
        },
        {
            "name": "ushshhw",
            "isOwner": false,
            "isOfficer": false,
            "joinDate": 1488761484,
            "troopsDonated": 0,
            "troopsReceived": 4,
            "rank": 16,
            "hqLevel": 2,
            "reputationInvested": 0,
            "xp": 149,
            "score": 100,
            "warParty": 0,
            "tournamentRating": 0,
            "tournamentScores": null,
            "attacksWon": 0,
            "defensesWon": 0,
            "planet": "planet1",
            "lastLoginTime": 1488760887,
            "lastUpdated": 1488761485,
            "hasPlanetaryCommand": false,
            "playerId": "18794ea4-0203-11e7-866f-061c98004f78"
        },
        {
            "name": "Yoda Halyapin",
            "isOwner": false,
            "isOfficer": false,
            "joinDate": 1490197109,
            "troopsDonated": 4,
            "troopsReceived": 12,
            "rank": 16,
            "hqLevel": 3,
            "reputationInvested": 0,
            "xp": 237,
            "score": 100,
            "warParty": 1,
            "tournamentRating": 0,
            "tournamentScores": {
                "planet23": 0,
                "planet8": 0
            },
            "attacksWon": 2,
            "defensesWon": 0,
            "planet": "planet1",
            "lastLoginTime": 1490413148,
            "lastUpdated": 1490413156,
            "hasPlanetaryCommand": false,
            "playerId": "52edae00-0e45-11e7-8d08-061c98004f78"
        },
        {
            "name": "Асасін",
            "isOwner": false,
            "isOfficer": false,
            "joinDate": 1490466256,
            "troopsDonated": 0,
            "troopsReceived": 0,
            "rank": 16,
            "hqLevel": 3,
            "reputationInvested": 0,
            "xp": 276,
            "score": 100,
            "warParty": 0,
            "tournamentRating": 0,
            "tournamentScores": {
                "planet23": 0,
                "planet8": 0
            },
            "attacksWon": 0,
            "defensesWon": 0,
            "planet": "planet1",
            "lastLoginTime": 1490471220,
            "lastUpdated": 1490471224,
            "hasPlanetaryCommand": false,
            "playerId": "3b9e51ab-1126-11e7-ba69-06c66a004f76"
        },
        {
            "name": "baze",
            "isOwner": false,
            "isOfficer": false,
            "joinDate": 1489931144,
            "troopsDonated": 0,
            "troopsReceived": 4,
            "rank": 20,
            "hqLevel": 2,
            "reputationInvested": 0,
            "xp": 123,
            "score": 99,
            "warParty": 0,
            "tournamentRating": 0,
            "tournamentScores": {
                "planet23": 0,
                "planet8": 0
            },
            "attacksWon": 2,
            "defensesWon": 0,
            "planet": "planet1",
            "lastLoginTime": 1490373946,
            "lastUpdated": 1490374111,
            "hasPlanetaryCommand": false,
            "playerId": "92059c9a-ccef-11e6-8705-061c98004f78"
        },
        {
            "name": "speedy",
            "isOwner": false,
            "isOfficer": false,
            "joinDate": 1487980874,
            "troopsDonated": 0,
            "troopsReceived": 0,
            "rank": 21,
            "hqLevel": 2,
            "reputationInvested": 0,
            "xp": 193,
            "score": 97,
            "warParty": 0,
            "tournamentRating": 0,
            "tournamentScores": {
                "planet23": 0,
                "planet8": 0
            },
            "attacksWon": 5,
            "defensesWon": 0,
            "planet": "planet1",
            "lastLoginTime": 1489195579,
            "lastUpdated": 1490479509,
            "hasPlanetaryCommand": false,
            "playerId": "3625140a-9d51-11e6-8034-069da4004f8b"
        },
        {
            "name": "construtor 01",
            "isOwner": false,
            "isOfficer": false,
            "joinDate": 1488057706,
            "troopsDonated": 0,
            "troopsReceived": 0,
            "rank": 22,
            "hqLevel": 2,
            "reputationInvested": 0,
            "xp": 123,
            "score": 96,
            "warParty": 0,
            "tournamentRating": 0,
            "tournamentScores": {
                "planet23": 0,
                "planet3": 0
            },
            "attacksWon": 0,
            "defensesWon": 0,
            "planet": "planet1",
            "lastLoginTime": 1488056613,
            "lastUpdated": 1488057857,
            "hasPlanetaryCommand": false,
            "playerId": "6d799325-fb9d-11e6-9158-06cb44004f79"
        },
        {
            "name": "hhgfccgxdcv",
            "isOwner": false,
            "isOfficer": false,
            "joinDate": 1488297899,
            "troopsDonated": 0,
            "troopsReceived": 4,
            "rank": 22,
            "hqLevel": 2,
            "reputationInvested": 0,
            "xp": 125,
            "score": 96,
            "warParty": 0,
            "tournamentRating": 0,
            "tournamentScores": {},
            "attacksWon": 0,
            "defensesWon": 0,
            "planet": "planet1",
            "lastLoginTime": 1488297709,
            "lastUpdated": 1488298220,
            "hasPlanetaryCommand": false,
            "playerId": "06d436e8-fdce-11e6-9158-06cb44004f79"
        },
        {
            "name": "001",
            "isOwner": false,
            "isOfficer": false,
            "joinDate": 1488884580,
            "troopsDonated": 0,
            "troopsReceived": 4,
            "rank": 24,
            "hqLevel": 3,
            "reputationInvested": 0,
            "xp": 238,
            "score": 94,
            "warParty": 0,
            "tournamentRating": 0,
            "tournamentScores": {
                "planet23": 0,
                "planet8": 0
            },
            "attacksWon": 0,
            "defensesWon": 0,
            "planet": "planet1",
            "lastLoginTime": 1488883302,
            "lastUpdated": 1490392223,
            "hasPlanetaryCommand": false,
            "playerId": "0a788701-031f-11e7-8bc5-060a32004f8c"
        },
        {
            "name": "Lee Kenobi",
            "isOwner": false,
            "isOfficer": false,
            "joinDate": 1488923509,
            "troopsDonated": 12,
            "troopsReceived": 8,
            "rank": 25,
            "hqLevel": 4,
            "reputationInvested": 0,
            "xp": 452,
            "score": 87,
            "warParty": 1,
            "tournamentRating": 0,
            "tournamentScores": {
                "planet23": 0,
                "planet8": 0
            },
            "attacksWon": 2,
            "defensesWon": 1,
            "planet": "planet1",
            "lastLoginTime": 1490202234,
            "lastUpdated": 1490462084,
            "hasPlanetaryCommand": false,
            "playerId": "cddb9ffb-02b8-11e7-8648-063864004f75"
        },
        {
            "name": "Blooded Wolf",
            "isOwner": false,
            "isOfficer": false,
            "joinDate": 1479833190,
            "troopsDonated": 19,
            "troopsReceived": 30,
            "rank": 26,
            "hqLevel": 3,
            "reputationInvested": 0,
            "xp": 360,
            "score": 56,
            "warParty": 1,
            "tournamentRating": 0,
            "tournamentScores": {
                "planet23": 0,
                "planet8": 0
            },
            "attacksWon": 3,
            "defensesWon": 1,
            "planet": "planet1",
            "lastLoginTime": 1490486931,
            "lastUpdated": 1490486935,
            "hasPlanetaryCommand": false,
            "playerId": "c13f66ca-a2a5-11e6-ab29-06a77e004fbb"
        },
        {
            "name": "danny1990",
            "isOwner": false,
            "isOfficer": false,
            "joinDate": 1488148602,
            "troopsDonated": 4,
            "troopsReceived": 7,
            "rank": 27,
            "hqLevel": 3,
            "reputationInvested": 0,
            "xp": 387,
            "score": 21,
            "warParty": 1,
            "tournamentRating": 0,
            "tournamentScores": {
                "planet23": 0,
                "planet8": 0
            },
            "attacksWon": 0,
            "defensesWon": 0,
            "planet": "planet1",
            "lastLoginTime": 1489756274,
            "lastUpdated": 1490461018,
            "hasPlanetaryCommand": false,
            "playerId": "3956d1b2-fc46-11e6-bfa6-06033c004f77"
        },
        {
            "name": "alucard",
            "isOwner": false,
            "isOfficer": false,
            "joinDate": 1486148885,
            "troopsDonated": 0,
            "troopsReceived": 0,
            "rank": 28,
            "hqLevel": 3,
            "reputationInvested": 0,
            "xp": 374,
            "score": 4,
            "warParty": 0,
            "tournamentRating": 0,
            "tournamentScores": {
                "planet23": 0,
                "planet8": 0
            },
            "attacksWon": 20,
            "defensesWon": 1,
            "planet": "planet1",
            "lastLoginTime": 1488716610,
            "lastUpdated": 1490383898,
            "hasPlanetaryCommand": false,
            "playerId": "b0d5c4de-e723-11e6-a0d9-061c98004f78"
        },
        {
            "name": "steve",
            "isOwner": false,
            "isOfficer": false,
            "joinDate": 1484683294,
            "troopsDonated": 20,
            "troopsReceived": 8,
            "rank": 29,
            "hqLevel": 6,
            "reputationInvested": 0,
            "xp": 843,
            "score": 1,
            "warParty": 1,
            "tournamentRating": 0,
            "tournamentScores": {
                "planet23": 0,
                "planet8": 0
            },
            "attacksWon": 4,
            "defensesWon": 6,
            "planet": "planet3",
            "lastLoginTime": 1490478767,
            "lastUpdated": 1490478771,
            "hasPlanetaryCommand": true,
            "playerId": "dc7b87a2-dcc5-11e6-97e5-06cb44004f79"
        },
        {
            "name": "цвывфафкшугехот",
            "isOwner": false,
            "isOfficer": false,
            "joinDate": 1486052660,
            "troopsDonated": 0,
            "troopsReceived": 19,
            "rank": 29,
            "hqLevel": 2,
            "reputationInvested": 0,
            "xp": 229,
            "score": 1,
            "warParty": 0,
            "tournamentRating": 0,
            "tournamentScores": {},
            "attacksWon": 9,
            "defensesWon": 3,
            "planet": "planet1",
            "lastLoginTime": 1487932757,
            "lastUpdated": 1490202866,
            "hasPlanetaryCommand": false,
            "playerId": "07b23dd5-0197-11e6-a115-061c98004f78"
        }
    ],
    "created": 1463243931,
    "highestRankAchieved": null,
    "activeMemberCount": 15,
    "squadWarReadyCount": 20,
    "currentWarId": "0395397b-10dc-11e7-84ee-06a77e004fbb",
    "warSignUpTime": null,
    "warRating": null,
    "isSameFactionWarAllowed": true,
    "score": 22095,
    "rank": 0,
    "id": "5959dc5b-19f2-11e6-9a6f-060a32004f8c",
    "memberCount": 30,
    "warHistory": [
        {
            "warId": "f080908d-a34f-11e6-9599-06cb44004f79",
            "endDate": 1478520266,
            "score": 9,
            "opponentScore": 14,
            "opponentGuildId": "93f9b2b0-93d9-11e6-9abd-060a32004f8c",
            "opponentName": "SHADOWEMPIREUK",
            "opponentIcon": "SquadSymbols_13"
        },
        {
            "warId": "ea19e1a9-a791-11e6-8dfd-061c98004f78",
            "endDate": 1478988377,
            "score": 9,
            "opponentScore": 15,
            "opponentGuildId": "1ce1c56d-611e-11e6-b250-06e6ee004fbc",
            "opponentName": "_Russia_Empire_",
            "opponentIcon": "SquadSymbols_09"
        },
        {
            "warId": "40c66268-ada9-11e6-9d2a-06dc8c004fbd",
            "endDate": 1479658109,
            "score": 15,
            "opponentScore": 14,
            "opponentGuildId": "bc21fe08-6ac3-11e6-a6e5-06a77e004fbb",
            "opponentName": "ImpWarMachine",
            "opponentIcon": "SquadSymbols_15"
        },
        {
            "warId": "eb2cf820-b32a-11e6-9494-063864004f75",
            "endDate": 1480263948,
            "score": 14,
            "opponentScore": 2,
            "opponentGuildId": "8814835f-3f74-11e5-9d4a-06e6ee004fbc",
            "opponentName": "Deutsch-Imperia",
            "opponentIcon": "SquadSymbols_01"
        },
        {
            "warId": "a04c9e08-b857-11e6-8233-061c98004f78",
            "endDate": 1480832512,
            "score": 13,
            "opponentScore": 15,
            "opponentGuildId": "882b3f65-8567-11e6-8cb5-063864004f75",
            "opponentName": "SithOverlords",
            "opponentIcon": "SquadSymbols_15"
        },
        {
            "warId": "4825e04a-bd6f-11e6-9a3e-06033c004f77",
            "endDate": 1481393531,
            "score": 14,
            "opponentScore": 15,
            "opponentGuildId": "7b4316e7-5f77-11e6-ab5a-069da4004f8b",
            "opponentName": "CharlieOscar",
            "opponentIcon": ""
        },
        {
            "warId": "21efe48c-c392-11e6-b9bb-06c66a004f76",
            "endDate": 1482067105,
            "score": 15,
            "opponentScore": 14,
            "opponentGuildId": "8b526627-c2aa-11e5-a6b6-06e6ee004fbc",
            "opponentName": "Brauhof",
            "opponentIcon": "SquadSymbols_06"
        },
        {
            "warId": "34eb7b6c-c606-11e6-b88b-06a77e004fbb",
            "endDate": 1482339177,
            "score": 5,
            "opponentScore": 14,
            "opponentGuildId": "5c9a86e1-12cf-11e6-894d-06033c004f77",
            "opponentName": "stuff",
            "opponentIcon": "SquadSymbols_15"
        },
        {
            "warId": "1c6c8275-cce1-11e6-93f1-06a77e004fbb",
            "endDate": 1483090586,
            "score": 4,
            "opponentScore": 15,
            "opponentGuildId": "9f5bf64a-52ae-11e6-8dff-063864004f75",
            "opponentName": "DarkDecibels",
            "opponentIcon": "SquadSymbols_13"
        },
        {
            "warId": "92f24752-d412-11e6-b62a-06e6ee004fbc",
            "endDate": 1483881488,
            "score": 15,
            "opponentScore": 10,
            "opponentGuildId": "91bb92e3-cb75-11e6-8705-061c98004f78",
            "opponentName": "%d0%9a%d0%90%d0%a0%d0%a2%d0%95%d0%9b%d0%ac",
            "opponentIcon": "SquadSymbols_13"
        },
        {
            "warId": "f73a228b-d8f8-11e6-95c1-063864004f75",
            "endDate": 1484420246,
            "score": 15,
            "opponentScore": 14,
            "opponentGuildId": "21c00400-27d4-11e5-ad3f-06a77e004fbb",
            "opponentName": "PhilippinesForce",
            "opponentIcon": "SquadSymbols_02"
        },
        {
            "warId": "fc9939b5-df1b-11e6-886d-069da4004f8b",
            "endDate": 1485094994,
            "score": 39,
            "opponentScore": 33,
            "opponentGuildId": "488968e1-5971-11e6-8f45-06033c004f77",
            "opponentName": "4.Ordnung",
            "opponentIcon": "SquadSymbols_11"
        },
        {
            "warId": "c10eeea5-e4ba-11e6-a7d6-06e6ee004fbc",
            "endDate": 1485712940,
            "score": 40,
            "opponentScore": 20,
            "opponentGuildId": "70498ac7-3e8c-11e6-8216-069da4004f8b",
            "opponentName": "Espadas",
            "opponentIcon": "SquadSymbols_01"
        },
        {
            "warId": "e0635b1e-ea36-11e6-add6-06e6ee004fbc",
            "endDate": 1486316009,
            "score": 27,
            "opponentScore": 45,
            "opponentGuildId": "882b3f65-8567-11e6-8cb5-063864004f75",
            "opponentName": "SithOverlords",
            "opponentIcon": "SquadSymbols_15"
        },
        {
            "warId": "a023bf3b-efcd-11e6-9009-06dc8c004fbd",
            "endDate": 1486930537,
            "score": 19,
            "opponentScore": 31,
            "opponentGuildId": "488968e1-5971-11e6-8f45-06033c004f77",
            "opponentName": "4.Ordnung",
            "opponentIcon": "SquadSymbols_11"
        },
        {
            "warId": "1e65b68a-f4e1-11e6-8841-060a32004f8c",
            "endDate": 1487488636,
            "score": 37,
            "opponentScore": 37,
            "opponentGuildId": "b4646c18-7257-11e6-b931-06a77e004fbb",
            "opponentName": "DeutschNr1",
            "opponentIcon": "SquadSymbols_13"
        },
        {
            "warId": "f6abe679-f9bb-11e6-9750-069da4004f8b",
            "endDate": 1488022435,
            "score": 30,
            "opponentScore": 33,
            "opponentGuildId": "6d19ff99-408f-11e6-b914-06cb44004f79",
            "opponentName": "Portugal%c2%ae",
            "opponentIcon": "SquadSymbols_06"
        },
        {
            "warId": "8feb0858-00a8-11e7-8648-063864004f75",
            "endDate": 1488783758,
            "score": 29,
            "opponentScore": 35,
            "opponentGuildId": "840bbf3f-d770-11e6-b64c-06a77e004fbb",
            "opponentName": "DangerSeeker",
            "opponentIcon": "SquadSymbols_07"
        },
        {
            "warId": "0fb01339-0596-11e7-9902-06cb44004f79",
            "endDate": 1489325567,
            "score": 29,
            "opponentScore": 39,
            "opponentGuildId": "a186de61-4cda-11e5-adae-06e6ee004fbc",
            "opponentName": "Outerlimits",
            "opponentIcon": "SquadSymbols_13"
        },
        {
            "warId": "e8c33a88-0b4f-11e7-b35e-06e6ee004fbc",
            "endDate": 1489955196,
            "score": 36,
            "opponentScore": 31,
            "opponentGuildId": "8c5f19c0-a617-11e6-bcbb-061c98004f78",
            "opponentName": "Wehrmacht1488",
            "opponentIcon": "SquadSymbols_09"
        }
    ],
    "level": 22,
    "totalRepInvested": 955,
    "perks": {
        "available": {
            "CBar_CFac": "perk_CBar_CFac4",
            "DntAmt_DntT": "perk_DntAmt_DntT4",
            "GCon_TDrd": "perk_GCon_TDrd4",
            "GCon_DntT": "perk_GCon_DntT4",
            "CHro_GAll": "perk_CHro_GAll4",
            "GCrd_GCon": "perk_GCrd_GCon3",
            "CCan_TDrd": "perk_CCan_TDrd4",
            "TDrd": "perk_TDrd4",
            "CBar_CCan": "perk_CBar_CCan5",
            "CFac_CCan": "perk_CFac_CCan3",
            "GAll_GCon": "perk_GAll_GCon2"
        },
        "inProgress": {
            "perk_CBar_CFac5": 55
        }
    },
    "lastPerkNotif": 1489407463
}
